[
  {
    "t1FGA2": 54,
    "t2FGA2": 50,
    "t1FGM2": 27,
    "t2FGM2": 25,
    "t1FGA3": 35,
    "t2FGA3": 29,
    "t1FGM3": 14,
    "t2FGM3": 8,
    "t1FTA": 25,
    "t2FTA": 23,
    "t1FTM": 22,
    "t2FTM": 16,
    "t1FTPercent": 88,
    "t2FTPercent": 69.57,
    "t1FG3Percent": 40,
    "t2FG3Percent": 27.59,
    "t1FG2Percent": 50,
    "t2FG2Percent": 50,
    "t1TO": 12,
    "t2TO": 14,
    "t1Rbs": 44,
    "t2Rbs": 40,
    "t1Ass": 24,
    "t2Ass": 28,
    "t1Fls": 14,
    "t2Fls": 16,
    "t1Pts": 118,
    "t2Pts": 90
  },
  {
    "t1FGA2": 53,
    "t2FGA2": 56,
    "t1FGM2": 21,
    "t2FGM2": 22,
    "t1FGA3": 31,
    "t2FGA3": 22,
    "t1FGM3": 9,
    "t2FGM3": 6,
    "t1FTA": 30,
    "t2FTA": 17,
    "t1FTM": 27,
    "t2FTM": 11,
    "t1FTPercent": 90,
    "t2FTPercent": 64.71,
    "t1FG3Percent": 29.03,
    "t2FG3Percent": 27.27,
    "t1FG2Percent": 39.62,
    "t2FG2Percent": 39.29,
    "t1TO": 5,
    "t2TO": 8,
    "t1Rbs": 52,
    "t2Rbs": 51,
    "t1Ass": 16,
    "t2Ass": 16,
    "t1Fls": 14,
    "t2Fls": 14,
    "t1Pts": 96,
    "t2Pts": 73
  },
  {
    "t1FGA2": 67,
    "t2FGA2": 88,
    "t1FGM2": 33,
    "t2FGM2": 35,
    "t1FGA3": 33,
    "t2FGA3": 32,
    "t1FGM3": 9,
    "t2FGM3": 12,
    "t1FTA": 10,
    "t2FTA": 17,
    "t1FTM": 9,
    "t2FTM": 11,
    "t1FTPercent": 90,
    "t2FTPercent": 64.71,
    "t1FG3Percent": 27.27,
    "t2FG3Percent": 37.5,
    "t1FG2Percent": 49.25,
    "t2FG2Percent": 39.77,
    "t1TO": 13,
    "t2TO": 15,
    "t1Rbs": 46,
    "t2Rbs": 55,
    "t1Ass": 15,
    "t2Ass": 16,
    "t1Fls": 16,
    "t2Fls": 17,
    "t1Pts": 102,
    "t2Pts": 117
  },
  {
    "t1FGA2": 78,
    "t2FGA2": 87,
    "t1FGM2": 31,
    "t2FGM2": 34,
    "t1FGA3": 31,
    "t2FGA3": 26,
    "t1FGM3": 12,
    "t2FGM3": 10,
    "t1FTA": 17,
    "t2FTA": 25,
    "t1FTM": 15,
    "t2FTM": 17,
    "t1FTPercent": 88.24,
    "t2FTPercent": 68,
    "t1FG3Percent": 38.71,
    "t2FG3Percent": 38.46,
    "t1FG2Percent": 39.74,
    "t2FG2Percent": 39.08,
    "t1TO": 6,
    "t2TO": 8,
    "t1Rbs": 48,
    "t2Rbs": 45,
    "t1Ass": 18,
    "t2Ass": 15,
    "t1Fls": 15,
    "t2Fls": 13,
    "t1Pts": 113,
    "t2Pts": 115
  },
  {
    "t1FGA2": 78,
    "t2FGA2": 89,
    "t1FGM2": 31,
    "t2FGM2": 44,
    "t1FGA3": 32,
    "t2FGA3": 23,
    "t1FGM3": 12,
    "t2FGM3": 9,
    "t1FTA": 30,
    "t2FTA": 13,
    "t1FTM": 27,
    "t2FTM": 9,
    "t1FTPercent": 90,
    "t2FTPercent": 69.23,
    "t1FG3Percent": 37.5,
    "t2FG3Percent": 39.13,
    "t1FG2Percent": 39.74,
    "t2FG2Percent": 49.44,
    "t1TO": 5,
    "t2TO": 5,
    "t1Rbs": 58,
    "t2Rbs": 46,
    "t1Ass": 26,
    "t2Ass": 15,
    "t1Fls": 13,
    "t2Fls": 20,
    "t1Pts": 125,
    "t2Pts": 124
  },
  {
    "t1FGA2": 89,
    "t2FGA2": 61,
    "t1FGM2": 35,
    "t2FGM2": 24,
    "t1FGA3": 26,
    "t2FGA3": 38,
    "t1FGM3": 7,
    "t2FGM3": 15,
    "t1FTA": 20,
    "t2FTA": 14,
    "t1FTM": 18,
    "t2FTM": 9,
    "t1FTPercent": 90,
    "t2FTPercent": 64.29,
    "t1FG3Percent": 26.92,
    "t2FG3Percent": 39.47,
    "t1FG2Percent": 39.33,
    "t2FG2Percent": 39.34,
    "t1TO": 5,
    "t2TO": 14,
    "t1Rbs": 40,
    "t2Rbs": 50,
    "t1Ass": 20,
    "t2Ass": 24,
    "t1Fls": 15,
    "t2Fls": 14,
    "t1Pts": 109,
    "t2Pts": 102
  },
  {
    "t1FGA2": 62,
    "t2FGA2": 57,
    "t1FGM2": 31,
    "t2FGM2": 28,
    "t1FGA3": 40,
    "t2FGA3": 25,
    "t1FGM3": 16,
    "t2FGM3": 7,
    "t1FTA": 23,
    "t2FTA": 15,
    "t1FTM": 20,
    "t2FTM": 13,
    "t1FTPercent": 86.96,
    "t2FTPercent": 86.67,
    "t1FG3Percent": 40,
    "t2FG3Percent": 28,
    "t1FG2Percent": 50,
    "t2FG2Percent": 49.12,
    "t1TO": 13,
    "t2TO": 15,
    "t1Rbs": 56,
    "t2Rbs": 42,
    "t1Ass": 29,
    "t2Ass": 28,
    "t1Fls": 12,
    "t2Fls": 10,
    "t1Pts": 130,
    "t2Pts": 90
  },
  {
    "t1FGA2": 49,
    "t2FGA2": 50,
    "t1FGM2": 19,
    "t2FGM2": 20,
    "t1FGA3": 34,
    "t2FGA3": 28,
    "t1FGM3": 13,
    "t2FGM3": 11,
    "t1FTA": 26,
    "t2FTA": 30,
    "t1FTM": 18,
    "t2FTM": 21,
    "t1FTPercent": 69.23,
    "t2FTPercent": 70,
    "t1FG3Percent": 38.24,
    "t2FG3Percent": 39.29,
    "t1FG2Percent": 38.78,
    "t2FG2Percent": 40,
    "t1TO": 10,
    "t2TO": 8,
    "t1Rbs": 44,
    "t2Rbs": 48,
    "t1Ass": 27,
    "t2Ass": 16,
    "t1Fls": 20,
    "t2Fls": 12,
    "t1Pts": 95,
    "t2Pts": 94
  },
  {
    "t1FGA2": 82,
    "t2FGA2": 83,
    "t1FGM2": 41,
    "t2FGM2": 41,
    "t1FGA3": 24,
    "t2FGA3": 23,
    "t1FGM3": 7,
    "t2FGM3": 9,
    "t1FTA": 27,
    "t2FTA": 26,
    "t1FTM": 18,
    "t2FTM": 23,
    "t1FTPercent": 66.67,
    "t2FTPercent": 88.46,
    "t1FG3Percent": 29.17,
    "t2FG3Percent": 39.13,
    "t1FG2Percent": 50,
    "t2FG2Percent": 49.4,
    "t1TO": 6,
    "t2TO": 5,
    "t1Rbs": 53,
    "t2Rbs": 50,
    "t1Ass": 19,
    "t2Ass": 25,
    "t1Fls": 11,
    "t2Fls": 11,
    "t1Pts": 121,
    "t2Pts": 132
  },
  {
    "t1FGA2": 62,
    "t2FGA2": 48,
    "t1FGM2": 31,
    "t2FGM2": 19,
    "t1FGA3": 33,
    "t2FGA3": 25,
    "t1FGM3": 9,
    "t2FGM3": 7,
    "t1FTA": 23,
    "t2FTA": 11,
    "t1FTM": 20,
    "t2FTM": 7,
    "t1FTPercent": 86.96,
    "t2FTPercent": 63.64,
    "t1FG3Percent": 27.27,
    "t2FG3Percent": 28,
    "t1FG2Percent": 50,
    "t2FG2Percent": 39.58,
    "t1TO": 14,
    "t2TO": 15,
    "t1Rbs": 52,
    "t2Rbs": 46,
    "t1Ass": 27,
    "t2Ass": 26,
    "t1Fls": 15,
    "t2Fls": 14,
    "t1Pts": 109,
    "t2Pts": 66
  },
  {
    "t1FGA2": 67,
    "t2FGA2": 45,
    "t1FGM2": 33,
    "t2FGM2": 22,
    "t1FGA3": 20,
    "t2FGA3": 36,
    "t1FGM3": 8,
    "t2FGM3": 10,
    "t1FTA": 19,
    "t2FTA": 28,
    "t1FTM": 17,
    "t2FTM": 25,
    "t1FTPercent": 89.47,
    "t2FTPercent": 89.29,
    "t1FG3Percent": 40,
    "t2FG3Percent": 27.78,
    "t1FG2Percent": 49.25,
    "t2FG2Percent": 48.89,
    "t1TO": 14,
    "t2TO": 15,
    "t1Rbs": 47,
    "t2Rbs": 45,
    "t1Ass": 17,
    "t2Ass": 21,
    "t1Fls": 20,
    "t2Fls": 20,
    "t1Pts": 107,
    "t2Pts": 99
  },
  {
    "t1FGA2": 79,
    "t2FGA2": 86,
    "t1FGM2": 31,
    "t2FGM2": 34,
    "t1FGA3": 28,
    "t2FGA3": 20,
    "t1FGM3": 8,
    "t2FGM3": 6,
    "t1FTA": 26,
    "t2FTA": 12,
    "t1FTM": 23,
    "t2FTM": 10,
    "t1FTPercent": 88.46,
    "t2FTPercent": 83.33,
    "t1FG3Percent": 28.57,
    "t2FG3Percent": 30,
    "t1FG2Percent": 39.24,
    "t2FG2Percent": 39.53,
    "t1TO": 9,
    "t2TO": 6,
    "t1Rbs": 51,
    "t2Rbs": 57,
    "t1Ass": 27,
    "t2Ass": 16,
    "t1Fls": 15,
    "t2Fls": 19,
    "t1Pts": 109,
    "t2Pts": 96
  },
  {
    "t1FGA2": 67,
    "t2FGA2": 81,
    "t1FGM2": 33,
    "t2FGM2": 40,
    "t1FGA3": 33,
    "t2FGA3": 23,
    "t1FGM3": 9,
    "t2FGM3": 9,
    "t1FTA": 13,
    "t2FTA": 26,
    "t1FTM": 11,
    "t2FTM": 23,
    "t1FTPercent": 84.62,
    "t2FTPercent": 88.46,
    "t1FG3Percent": 27.27,
    "t2FG3Percent": 39.13,
    "t1FG2Percent": 49.25,
    "t2FG2Percent": 49.38,
    "t1TO": 5,
    "t2TO": 13,
    "t1Rbs": 40,
    "t2Rbs": 45,
    "t1Ass": 17,
    "t2Ass": 25,
    "t1Fls": 14,
    "t2Fls": 14,
    "t1Pts": 104,
    "t2Pts": 130
  },
  {
    "t1FGA2": 77,
    "t2FGA2": 55,
    "t1FGM2": 38,
    "t2FGM2": 22,
    "t1FGA3": 21,
    "t2FGA3": 26,
    "t1FGM3": 8,
    "t2FGM3": 10,
    "t1FTA": 17,
    "t2FTA": 10,
    "t1FTM": 15,
    "t2FTM": 9,
    "t1FTPercent": 88.24,
    "t2FTPercent": 90,
    "t1FG3Percent": 38.1,
    "t2FG3Percent": 38.46,
    "t1FG2Percent": 49.35,
    "t2FG2Percent": 40,
    "t1TO": 12,
    "t2TO": 6,
    "t1Rbs": 47,
    "t2Rbs": 42,
    "t1Ass": 18,
    "t2Ass": 18,
    "t1Fls": 15,
    "t2Fls": 19,
    "t1Pts": 115,
    "t2Pts": 83
  },
  {
    "t1FGA2": 82,
    "t2FGA2": 65,
    "t1FGM2": 41,
    "t2FGM2": 26,
    "t1FGA3": 26,
    "t2FGA3": 31,
    "t1FGM3": 7,
    "t2FGM3": 9,
    "t1FTA": 25,
    "t2FTA": 25,
    "t1FTM": 22,
    "t2FTM": 17,
    "t1FTPercent": 88,
    "t2FTPercent": 68,
    "t1FG3Percent": 26.92,
    "t2FG3Percent": 29.03,
    "t1FG2Percent": 50,
    "t2FG2Percent": 40,
    "t1TO": 9,
    "t2TO": 8,
    "t1Rbs": 44,
    "t2Rbs": 45,
    "t1Ass": 18,
    "t2Ass": 30,
    "t1Fls": 15,
    "t2Fls": 13,
    "t1Pts": 125,
    "t2Pts": 96
  },
  {
    "t1FGA2": 85,
    "t2FGA2": 83,
    "t1FGM2": 34,
    "t2FGM2": 33,
    "t1FGA3": 37,
    "t2FGA3": 33,
    "t1FGM3": 14,
    "t2FGM3": 13,
    "t1FTA": 15,
    "t2FTA": 26,
    "t1FTM": 10,
    "t2FTM": 23,
    "t1FTPercent": 66.67,
    "t2FTPercent": 88.46,
    "t1FG3Percent": 37.84,
    "t2FG3Percent": 39.39,
    "t1FG2Percent": 40,
    "t2FG2Percent": 39.76,
    "t1TO": 15,
    "t2TO": 15,
    "t1Rbs": 58,
    "t2Rbs": 49,
    "t1Ass": 19,
    "t2Ass": 20,
    "t1Fls": 11,
    "t2Fls": 17,
    "t1Pts": 120,
    "t2Pts": 128
  },
  {
    "t1FGA2": 89,
    "t2FGA2": 47,
    "t1FGM2": 35,
    "t2FGM2": 18,
    "t1FGA3": 26,
    "t2FGA3": 27,
    "t1FGM3": 7,
    "t2FGM3": 8,
    "t1FTA": 30,
    "t2FTA": 15,
    "t1FTM": 27,
    "t2FTM": 13,
    "t1FTPercent": 90,
    "t2FTPercent": 86.67,
    "t1FG3Percent": 26.92,
    "t2FG3Percent": 29.63,
    "t1FG2Percent": 39.33,
    "t2FG2Percent": 38.3,
    "t1TO": 11,
    "t2TO": 8,
    "t1Rbs": 42,
    "t2Rbs": 46,
    "t1Ass": 21,
    "t2Ass": 16,
    "t1Fls": 14,
    "t2Fls": 18,
    "t1Pts": 118,
    "t2Pts": 73
  },
  {
    "t1FGA2": 70,
    "t2FGA2": 55,
    "t1FGM2": 28,
    "t2FGM2": 22,
    "t1FGA3": 32,
    "t2FGA3": 34,
    "t1FGM3": 12,
    "t2FGM3": 13,
    "t1FTA": 28,
    "t2FTA": 18,
    "t1FTM": 19,
    "t2FTM": 16,
    "t1FTPercent": 67.86,
    "t2FTPercent": 88.89,
    "t1FG3Percent": 37.5,
    "t2FG3Percent": 38.24,
    "t1FG2Percent": 40,
    "t2FG2Percent": 40,
    "t1TO": 7,
    "t2TO": 7,
    "t1Rbs": 44,
    "t2Rbs": 45,
    "t1Ass": 19,
    "t2Ass": 30,
    "t1Fls": 15,
    "t2Fls": 11,
    "t1Pts": 111,
    "t2Pts": 99
  },
  {
    "t1FGA2": 48,
    "t2FGA2": 56,
    "t1FGM2": 19,
    "t2FGM2": 28,
    "t1FGA3": 26,
    "t2FGA3": 38,
    "t1FGM3": 10,
    "t2FGM3": 15,
    "t1FTA": 14,
    "t2FTA": 28,
    "t1FTM": 12,
    "t2FTM": 19,
    "t1FTPercent": 85.71,
    "t2FTPercent": 67.86,
    "t1FG3Percent": 38.46,
    "t2FG3Percent": 39.47,
    "t1FG2Percent": 39.58,
    "t2FG2Percent": 50,
    "t1TO": 15,
    "t2TO": 14,
    "t1Rbs": 50,
    "t2Rbs": 40,
    "t1Ass": 25,
    "t2Ass": 25,
    "t1Fls": 20,
    "t2Fls": 15,
    "t1Pts": 80,
    "t2Pts": 120
  },
  {
    "t1FGA2": 47,
    "t2FGA2": 51,
    "t1FGM2": 23,
    "t2FGM2": 20,
    "t1FGA3": 32,
    "t2FGA3": 35,
    "t1FGM3": 9,
    "t2FGM3": 10,
    "t1FTA": 14,
    "t2FTA": 30,
    "t1FTM": 9,
    "t2FTM": 21,
    "t1FTPercent": 64.29,
    "t2FTPercent": 70,
    "t1FG3Percent": 28.13,
    "t2FG3Percent": 28.57,
    "t1FG2Percent": 48.94,
    "t2FG2Percent": 39.22,
    "t1TO": 9,
    "t2TO": 9,
    "t1Rbs": 59,
    "t2Rbs": 53,
    "t1Ass": 20,
    "t2Ass": 22,
    "t1Fls": 19,
    "t2Fls": 18,
    "t1Pts": 82,
    "t2Pts": 91
  },
  {
    "t1FGA2": 74,
    "t2FGA2": 47,
    "t1FGM2": 29,
    "t2FGM2": 18,
    "t1FGA3": 22,
    "t2FGA3": 33,
    "t1FGM3": 6,
    "t2FGM3": 9,
    "t1FTA": 13,
    "t2FTA": 15,
    "t1FTM": 9,
    "t2FTM": 10,
    "t1FTPercent": 69.23,
    "t2FTPercent": 66.67,
    "t1FG3Percent": 27.27,
    "t2FG3Percent": 27.27,
    "t1FG2Percent": 39.19,
    "t2FG2Percent": 38.3,
    "t1TO": 11,
    "t2TO": 15,
    "t1Rbs": 40,
    "t2Rbs": 45,
    "t1Ass": 18,
    "t2Ass": 24,
    "t1Fls": 17,
    "t2Fls": 17,
    "t1Pts": 85,
    "t2Pts": 73
  },
  {
    "t1FGA2": 79,
    "t2FGA2": 86,
    "t1FGM2": 31,
    "t2FGM2": 43,
    "t1FGA3": 40,
    "t2FGA3": 40,
    "t1FGM3": 12,
    "t2FGM3": 16,
    "t1FTA": 15,
    "t2FTA": 11,
    "t1FTM": 13,
    "t2FTM": 7,
    "t1FTPercent": 86.67,
    "t2FTPercent": 63.64,
    "t1FG3Percent": 30,
    "t2FG3Percent": 40,
    "t1FG2Percent": 39.24,
    "t2FG2Percent": 50,
    "t1TO": 14,
    "t2TO": 7,
    "t1Rbs": 42,
    "t2Rbs": 60,
    "t1Ass": 18,
    "t2Ass": 16,
    "t1Fls": 14,
    "t2Fls": 12,
    "t1Pts": 111,
    "t2Pts": 141
  },
  {
    "t1FGA2": 83,
    "t2FGA2": 88,
    "t1FGM2": 33,
    "t2FGM2": 35,
    "t1FGA3": 30,
    "t2FGA3": 39,
    "t1FGM3": 9,
    "t2FGM3": 15,
    "t1FTA": 29,
    "t2FTA": 15,
    "t1FTM": 26,
    "t2FTM": 10,
    "t1FTPercent": 89.66,
    "t2FTPercent": 66.67,
    "t1FG3Percent": 30,
    "t2FG3Percent": 38.46,
    "t1FG2Percent": 39.76,
    "t2FG2Percent": 39.77,
    "t1TO": 7,
    "t2TO": 15,
    "t1Rbs": 44,
    "t2Rbs": 59,
    "t1Ass": 15,
    "t2Ass": 15,
    "t1Fls": 13,
    "t2Fls": 14,
    "t1Pts": 119,
    "t2Pts": 125
  },
  {
    "t1FGA2": 56,
    "t2FGA2": 78,
    "t1FGM2": 22,
    "t2FGM2": 39,
    "t1FGA3": 28,
    "t2FGA3": 20,
    "t1FGM3": 11,
    "t2FGM3": 6,
    "t1FTA": 23,
    "t2FTA": 19,
    "t1FTM": 16,
    "t2FTM": 13,
    "t1FTPercent": 69.57,
    "t2FTPercent": 68.42,
    "t1FG3Percent": 39.29,
    "t2FG3Percent": 30,
    "t1FG2Percent": 39.29,
    "t2FG2Percent": 50,
    "t1TO": 7,
    "t2TO": 15,
    "t1Rbs": 47,
    "t2Rbs": 45,
    "t1Ass": 21,
    "t2Ass": 19,
    "t1Fls": 11,
    "t2Fls": 12,
    "t1Pts": 93,
    "t2Pts": 109
  },
  {
    "t1FGA2": 88,
    "t2FGA2": 82,
    "t1FGM2": 44,
    "t2FGM2": 32,
    "t1FGA3": 27,
    "t2FGA3": 33,
    "t1FGM3": 10,
    "t2FGM3": 9,
    "t1FTA": 27,
    "t2FTA": 14,
    "t1FTM": 24,
    "t2FTM": 9,
    "t1FTPercent": 88.89,
    "t2FTPercent": 64.29,
    "t1FG3Percent": 37.04,
    "t2FG3Percent": 27.27,
    "t1FG2Percent": 50,
    "t2FG2Percent": 39.02,
    "t1TO": 10,
    "t2TO": 12,
    "t1Rbs": 57,
    "t2Rbs": 47,
    "t1Ass": 25,
    "t2Ass": 21,
    "t1Fls": 19,
    "t2Fls": 19,
    "t1Pts": 142,
    "t2Pts": 100
  },
  {
    "t1FGA2": 49,
    "t2FGA2": 76,
    "t1FGM2": 19,
    "t2FGM2": 30,
    "t1FGA3": 35,
    "t2FGA3": 23,
    "t1FGM3": 10,
    "t2FGM3": 9,
    "t1FTA": 18,
    "t2FTA": 12,
    "t1FTM": 12,
    "t2FTM": 10,
    "t1FTPercent": 66.67,
    "t2FTPercent": 83.33,
    "t1FG3Percent": 28.57,
    "t2FG3Percent": 39.13,
    "t1FG2Percent": 38.78,
    "t2FG2Percent": 39.47,
    "t1TO": 8,
    "t2TO": 10,
    "t1Rbs": 54,
    "t2Rbs": 57,
    "t1Ass": 28,
    "t2Ass": 27,
    "t1Fls": 18,
    "t2Fls": 13,
    "t1Pts": 80,
    "t2Pts": 97
  },
  {
    "t1FGA2": 84,
    "t2FGA2": 56,
    "t1FGM2": 33,
    "t2FGM2": 28,
    "t1FGA3": 25,
    "t2FGA3": 25,
    "t1FGM3": 7,
    "t2FGM3": 7,
    "t1FTA": 29,
    "t2FTA": 20,
    "t1FTM": 20,
    "t2FTM": 14,
    "t1FTPercent": 68.97,
    "t2FTPercent": 70,
    "t1FG3Percent": 28,
    "t2FG3Percent": 28,
    "t1FG2Percent": 39.29,
    "t2FG2Percent": 50,
    "t1TO": 12,
    "t2TO": 8,
    "t1Rbs": 54,
    "t2Rbs": 53,
    "t1Ass": 23,
    "t2Ass": 17,
    "t1Fls": 14,
    "t2Fls": 11,
    "t1Pts": 107,
    "t2Pts": 91
  },
  {
    "t1FGA2": 85,
    "t2FGA2": 87,
    "t1FGM2": 42,
    "t2FGM2": 43,
    "t1FGA3": 34,
    "t2FGA3": 31,
    "t1FGM3": 13,
    "t2FGM3": 12,
    "t1FTA": 26,
    "t2FTA": 12,
    "t1FTM": 23,
    "t2FTM": 8,
    "t1FTPercent": 88.46,
    "t2FTPercent": 66.67,
    "t1FG3Percent": 38.24,
    "t2FG3Percent": 38.71,
    "t1FG2Percent": 49.41,
    "t2FG2Percent": 49.43,
    "t1TO": 10,
    "t2TO": 15,
    "t1Rbs": 46,
    "t2Rbs": 57,
    "t1Ass": 29,
    "t2Ass": 18,
    "t1Fls": 12,
    "t2Fls": 15,
    "t1Pts": 146,
    "t2Pts": 130
  },
  {
    "t1FGA2": 80,
    "t2FGA2": 82,
    "t1FGM2": 32,
    "t2FGM2": 41,
    "t1FGA3": 33,
    "t2FGA3": 35,
    "t1FGM3": 9,
    "t2FGM3": 10,
    "t1FTA": 18,
    "t2FTA": 21,
    "t1FTM": 16,
    "t2FTM": 14,
    "t1FTPercent": 88.89,
    "t2FTPercent": 66.67,
    "t1FG3Percent": 27.27,
    "t2FG3Percent": 28.57,
    "t1FG2Percent": 40,
    "t2FG2Percent": 50,
    "t1TO": 9,
    "t2TO": 8,
    "t1Rbs": 43,
    "t2Rbs": 43,
    "t1Ass": 23,
    "t2Ass": 22,
    "t1Fls": 14,
    "t2Fls": 10,
    "t1Pts": 107,
    "t2Pts": 126
  },
  {
    "t1FGA2": 87,
    "t2FGA2": 88,
    "t1FGM2": 43,
    "t2FGM2": 35,
    "t1FGA3": 21,
    "t2FGA3": 31,
    "t1FGM3": 6,
    "t2FGM3": 9,
    "t1FTA": 27,
    "t2FTA": 19,
    "t1FTM": 18,
    "t2FTM": 13,
    "t1FTPercent": 66.67,
    "t2FTPercent": 68.42,
    "t1FG3Percent": 28.57,
    "t2FG3Percent": 29.03,
    "t1FG2Percent": 49.43,
    "t2FG2Percent": 39.77,
    "t1TO": 11,
    "t2TO": 12,
    "t1Rbs": 48,
    "t2Rbs": 46,
    "t1Ass": 21,
    "t2Ass": 20,
    "t1Fls": 17,
    "t2Fls": 11,
    "t1Pts": 122,
    "t2Pts": 110
  },
  {
    "t1FGA2": 90,
    "t2FGA2": 70,
    "t1FGM2": 36,
    "t2FGM2": 35,
    "t1FGA3": 25,
    "t2FGA3": 21,
    "t1FGM3": 10,
    "t2FGM3": 6,
    "t1FTA": 13,
    "t2FTA": 17,
    "t1FTM": 11,
    "t2FTM": 11,
    "t1FTPercent": 84.62,
    "t2FTPercent": 64.71,
    "t1FG3Percent": 40,
    "t2FG3Percent": 28.57,
    "t1FG2Percent": 40,
    "t2FG2Percent": 50,
    "t1TO": 8,
    "t2TO": 8,
    "t1Rbs": 57,
    "t2Rbs": 60,
    "t1Ass": 22,
    "t2Ass": 27,
    "t1Fls": 11,
    "t2Fls": 15,
    "t1Pts": 113,
    "t2Pts": 99
  }
]